.gitignore
LICENSE
MANIFEST.in
README.md
pyproject.toml
setup.py
test.py
plot/plot_analysis.py
plot/plot_interpolation.py
plot/plot_velocity.py
plot/plot_window_to_error.py
sp3/__init__.py
sp3/__main__.py
sp3/parse.py
sp3/provider.py
sp3/providers.json
sp3/satellite.py
sp3/satellites.json
sp3/timesystem.py
sp3/unix.py
sp3.egg-info/PKG-INFO
sp3.egg-info/SOURCES.txt
sp3.egg-info/dependency_links.txt
sp3.egg-info/requires.txt
sp3.egg-info/top_level.txt
test_products/ESA0MGNFIN_20213460000_01D_05M_ORB.SP3
test_products/emr21000.sp3
test_products/igr21882.sp3
test_products/nsgf.orb.ajisai.211220.v00.sp3