Metadata-Version: 2.1
Name: sp3
Version: 1.1.1
Summary: Download and interpolate precise satellite ephemeris (SP3)
Home-page: https://github.com/neuromorphicsystems/sp3
Author: Alexandre Marcireau
Author-email: alexandre.marcireau@gmail.com
License: UNKNOWN
Platform: UNKNOWN
Classifier: Programming Language :: Python :: 3
Classifier: License :: OSI Approved :: GNU General Public License v3 (GPLv3)
Classifier: Operating System :: OS Independent
License-File: LICENSE
